setup.py
lazyprop/__init__.py
lazyprop/lazyprop.py
lazyprop.egg-info/PKG-INFO
lazyprop.egg-info/SOURCES.txt
lazyprop.egg-info/dependency_links.txt
lazyprop.egg-info/top_level.txt
test/test_lazyprop.py