Metadata-Version: 1.1
Name: lazyprop
Version: 1.0.0
Summary: Decorator to make class properties load lazily and cache
Home-page: https://github.com/dbjohnson/lazyprop
Author: Bryan Johnson
Author-email: d.bryan.johnson@gmail.com
License: UNKNOWN
Download-URL: https://github.com/dbjohnson/lazyprop/tarball/1.0.0
Platform: UNKNOWN
